[
    {
        "link": "http://download.autisticlulu.com:25565/Modpacks/modpack_B-Sides.zip",
        "modpack": "B-Sides V1",
        "logo": "https://raw.githubusercontent.com/MeguminBOT/Rhythm-Engine-Wiki/main/packImages/bsides.png",
        "author": "Rhythm Engine Team",
        "fileName": "modpack_B-Sides.zip"
    },
    {
        "link": "http://download.autisticlulu.com:25565/Modpacks/modpack_The%20Full%20Ass%20Tricky%20Mod.zip",
        "modpack": "The Full Ass Tricky Mod",
        "logo": "https://raw.githubusercontent.com/MeguminBOT/Rhythm-Engine-Wiki/main/packImages/trickyclown.png",
        "author": "Rhythm Engine Team",
        "fileName": "modpack_The Full Ass Tricky Mod.zip"
    }
]
